{
  "$schema": "https://turbo.build/schema.json",
  "tasks": {
    "build": {
      "outputs": ["dist/**"]
    },
    "type-check": {
      "dependsOn": ["^type-check"]
    },
    "dev": {
      "persistent": true,
      "cache": false
    },
    "build:ssr": {
      "outputs": ["dist/**"],
      "cache": false
    },
    "dev:ssr": {
      "cache": false,
      "persistent": true
    },
    "dev:server": {
      "cache": false,
      "persistent": true
    },
    "start:ssr": {
      "cache": false,
      "persistent": true
    },
    "clean": {}
  }
}
